Metadata-Version: 1.0
Name: jenkins2api
Version: 0.1
Summary: A jenkins api
Home-page: https://github.com/dineshdh/jenkins2api
Author: Dinesh Dharmawardena
Author-email: dinesh_dh@outlook.com
License: MIT
Platform: UNKNOWN
